dask_hpcconfig/__init__.py
dask_hpcconfig/__main__.py
dask_hpcconfig/cli.py
dask_hpcconfig/clusters.py
dask_hpcconfig/clusters.yaml
dask_hpcconfig/definitions.py
dask_hpcconfig/processors.py
dask_hpcconfig/types.py
dask_hpcconfig-2025.6.0.dist-info/licenses/LICENSE
dask_hpcconfig-2025.6.0.dist-info/METADATA
dask_hpcconfig-2025.6.0.dist-info/WHEEL
dask_hpcconfig-2025.6.0.dist-info/entry_points.txt
dask_hpcconfig-2025.6.0.dist-info/top_level.txt
dask_hpcconfig-2025.6.0.dist-info/RECORD
