Metadata-Version: 2.4
Name: dask-hpcconfig
Version: 2025.6.0
Summary: Configuration for various dask clusters
Author: Justus Magin
License-Expression: MIT
Project-URL: Documentation, https://dask-hpcconfig.readthedocs.io
Project-URL: Repository, https://github.com/umr-lops/dask-hpcconfig
Requires-Python: >=3.10
License-File: LICENSE
Requires-Dist: pyyaml
Requires-Dist: dask>=2024.06.0
Requires-Dist: distributed>=2024.06.0
Provides-Extra: jobqueue
Requires-Dist: dask-jobqueue>=0.8; extra == "jobqueue"
Provides-Extra: cli
Requires-Dist: typer; extra == "cli"
Requires-Dist: rich; extra == "cli"
Requires-Dist: tornado; extra == "cli"
Dynamic: license-file
